mixins/__init__.py
mixins/add_mixin.py
mixins/memtrackable.py
mixins/seedable.py
mixins/timeable.py
mixins/utils.py
ml_mixins-0.2.2.dist-info/LICENSE
ml_mixins-0.2.2.dist-info/METADATA
ml_mixins-0.2.2.dist-info/WHEEL
ml_mixins-0.2.2.dist-info/top_level.txt
ml_mixins-0.2.2.dist-info/RECORD
