Metadata-Version: 2.2
Name: ml_mixins
Version: 0.2.2
Summary: A collection of useful mixins for machine learning development code.
Author-email: "Matthew B. A. McDermott" <mattmcdermott8@gmail.com>
Project-URL: Homepage, https://github.com/mmcdermott/ML_mixins
Project-URL: Bug Tracker, https://github.com/mmcdermott/ML_mixins/issues
Classifier: Programming Language :: Python :: 3
Classifier: License :: OSI Approved :: MIT License
Classifier: Operating System :: OS Independent
Requires-Python: >=3.10
License-File: LICENSE
Requires-Dist: numpy
Provides-Extra: memtrackable
Requires-Dist: memray; extra == "memtrackable"
Provides-Extra: dev
Requires-Dist: pre-commit<4; extra == "dev"
Provides-Extra: tests
Requires-Dist: pytest; extra == "tests"
Requires-Dist: pytest-cov; extra == "tests"
Requires-Dist: pytest-benchmark; extra == "tests"
